netpulse_sdk/__init__.py
netpulse_sdk/client.py
netpulse_sdk/config.py
netpulse_sdk/enums.py
netpulse_sdk/error.py
netpulse_sdk/job.py
netpulse_sdk/result.py
netpulse_sdk/types.py
netpulse_sdk/utils.py
netpulse_sdk/transport/__init__.py
netpulse_sdk/transport/http.py
netpulse_sdk-0.2.1.dist-info/licenses/LICENSE
netpulse_sdk-0.2.1.dist-info/METADATA
netpulse_sdk-0.2.1.dist-info/WHEEL
netpulse_sdk-0.2.1.dist-info/top_level.txt
netpulse_sdk-0.2.1.dist-info/RECORD
